__init__.py
ORC/OrcApiClient.py
ORC/__init__.py
build/__init__.py
build/lib/__init__.py
build/lib/ORC/OrcApiClient.py
build/lib/ORC/__init__.py
orcidentify-0.1.0.dist-info/METADATA
orcidentify-0.1.0.dist-info/WHEEL
orcidentify-0.1.0.dist-info/top_level.txt
orcidentify-0.1.0.dist-info/RECORD
