Metadata-Version: 2.4
Name: ORCIdentify
Version: 0.1.0
Summary: A ocr api client to identify graphical captcha.
Author: HeJinQing
Author-email: q.w.e.a.s@icloud.com
Requires-Dist: requests
Dynamic: author
Dynamic: author-email
Dynamic: requires-dist
Dynamic: summary
